rapydsdk/__init__.py
rapydsdk/sdk.py
rapydsdk/setup.py
rapydsdk/hooks/__init__.py
rapydsdk/hooks/hook.py
rapydsdk/models/Account.py
rapydsdk/models/ActivateCard200Response.py
rapydsdk/models/ActivateCardRequest.py
rapydsdk/models/Address.py
rapydsdk/models/AddressRequest.py
rapydsdk/models/AllRefunds200Response.py
rapydsdk/models/AttemptItem.py
rapydsdk/models/Beneficiary.py
rapydsdk/models/BinDetails.py
rapydsdk/models/CancelPayment200Response.py
rapydsdk/models/CancelPayout200Response.py
rapydsdk/models/CancelSubscription200Response.py
rapydsdk/models/CardIssuing.py
rapydsdk/models/CardIssuingMasked.py
rapydsdk/models/CardTransaction.py
rapydsdk/models/Category.py
rapydsdk/models/CheckoutPageResponse.py
rapydsdk/models/ClientDetailsObject.py
rapydsdk/models/CloseIssuing200Response.py
rapydsdk/models/Condition.py
rapydsdk/models/ConfirmPayout200Response.py
rapydsdk/models/Contact.py
rapydsdk/models/ContactBusiness.py
rapydsdk/models/CountryObject.py
rapydsdk/models/Coupon.py
rapydsdk/models/CreateAddress200Response.py
rapydsdk/models/CreateAddressRequest.py
rapydsdk/models/CreateBeneficiary200Response.py
rapydsdk/models/CreateBeneficiaryRequest.py
rapydsdk/models/CreateCoupon200Response.py
rapydsdk/models/CreateCouponRequest.py
rapydsdk/models/CreateCustomer200Response.py
rapydsdk/models/CreateCustomerPaymentMethod200Response.py
rapydsdk/models/CreateCustomerPaymentMethodRequest.py
rapydsdk/models/CreateCustomerRequest.py
rapydsdk/models/CreateEwalletContact200Response.py
rapydsdk/models/CreateEwalletContactRequest.py
rapydsdk/models/CreateHostedApplicationToken200Response.py
rapydsdk/models/CreateHostedApplicationTokenRequest.py
rapydsdk/models/CreateIssuing200Response.py
rapydsdk/models/CreateIssuingRequest.py
rapydsdk/models/CreateOrder200Response.py
rapydsdk/models/CreateOrderRequest.py
rapydsdk/models/CreatePayment200Response.py
rapydsdk/models/CreatePaymentRequest.py
rapydsdk/models/CreatePayout200Response.py
rapydsdk/models/CreatePayoutRequest.py
rapyd_sdk-1.0.5.dist-info/LICENSE
rapyd_sdk-1.0.5.dist-info/METADATA
rapyd_sdk-1.0.5.dist-info/WHEEL
rapyd_sdk-1.0.5.dist-info/top_level.txt
rapyd_sdk-1.0.5.dist-info/RECORD
