Metadata-Version: 2.1
Name: rapyd-sdk
Version: 1.0.5
Summary: This is Rapyd OpenAPI
License: MIT
Requires-Python: >=3.7
License-File: LICENSE
Requires-Dist: requests
Requires-Dist: http-exceptions
Provides-Extra: test
Requires-Dist: pytest ; extra == 'test'
Requires-Dist: responses ; extra == 'test'
